grunnur/__init__.py
grunnur/_adapter_base.py
grunnur/_adapter_cuda.mako
grunnur/_adapter_cuda.py
grunnur/_adapter_opencl.mako
grunnur/_adapter_opencl.py
grunnur/_api.py
grunnur/_array.py
grunnur/_array_metadata.py
grunnur/_buffer.py
grunnur/_context.py
grunnur/_device.py
grunnur/_device_discovery.py
grunnur/_modules.py
grunnur/_platform.py
grunnur/_program.py
grunnur/_queue.py
grunnur/_sorted_list.py
grunnur/_static.py
grunnur/_template.py
grunnur/_testing/__init__.py
grunnur/_testing/_mock_base.py
grunnur/_testing/_mock_factory.py
grunnur/_testing/_mock_pycuda.py
grunnur/_testing/_mock_pyopencl.py
grunnur/_utils.py
grunnur/_virtual_alloc.py
grunnur/_vsize.mako
grunnur/_vsize.py
grunnur/dtypes.py
grunnur/functions.mako
grunnur/functions.py
grunnur/py.typed
grunnur-0.6.0.dist-info/WHEEL
grunnur-0.6.0.dist-info/METADATA
grunnur-0.6.0.dist-info/licenses/LICENSE.md
grunnur-0.6.0.dist-info/RECORD
