Metadata-Version: 2.1
Name: grunnur
Version: 0.6.0
Summary: Uniform API for PyOpenCL and PyCUDA.
License: MIT
Author-email: Bogdan Opanchuk <bogdan@opanchuk.net>
Requires-Python: >=3.10
Requires-Dist: mako>=1
Requires-Dist: numpy>=2
Provides-Extra: docs
Requires-Dist: sphinx>=4; extra == "docs"
Requires-Dist: furo; extra == "docs"
Requires-Dist: setuptools-scm>=7; extra == "docs"
Provides-Extra: lint
Requires-Dist: mypy>=1.4; extra == "lint"
Requires-Dist: ruff>=0.2; extra == "lint"
Provides-Extra: pycuda
Requires-Dist: pycuda>=2019.1.1; extra == "pycuda"
Provides-Extra: pyopencl
Requires-Dist: pyopencl>=2025.2.6; extra == "pyopencl"
Provides-Extra: tests
Requires-Dist: pytest>=6; extra == "tests"
Requires-Dist: pytest-cov; extra == "tests"
Requires-Dist: pytest-grunnur>=0.3; extra == "tests"
Project-URL: homepage, https://github.com/fjarri/grunnur
